{".class":"MypyFile","_fullname":"chromadb.auth.token_authn","future_import_flags":[],"is_partial_stub_package":false,"is_stub":false,"names":{".class":"SymbolTable","AuthError":{".class":"SymbolTableNode","cross_ref":"chromadb.auth.AuthError","kind":"Gdef","module_public":false},"ChromaAuthError":{".class":"SymbolTableNode","cross_ref":"chromadb.errors.ChromaAuthError","kind":"Gdef","module_public":false},"ClientAuthHeaders":{".class":"SymbolTableNode","cross_ref":"chromadb.auth.ClientAuthHeaders","kind":"Gdef","module_public":false},"ClientAuthProvider":{".class":"SymbolTableNode","cross_ref":"chromadb.auth.ClientAuthProvider","kind":"Gdef","module_public":false},"Dict":{".class":"SymbolTableNode","cross_ref":"typing.Dict","kind":"Gdef","module_public":false},"Enum":{".class":"SymbolTableNode","cross_ref":"enum.Enum","kind":"Gdef","module_public":false},"List":{".class":"SymbolTableNode","cross_ref":"typing.List","kind":"Gdef","module_public":false},"OpenTelemetryGranularity":{".class":"SymbolTableNode","cross_ref":"chromadb.telemetry.opentelemetry.OpenTelemetryGranularity","kind":"Gdef","module_public":false},"Optional":{".class":"SymbolTableNode","cross_ref":"typing.Optional","kind":"Gdef","module_public":false},"SecretStr":{".class":"SymbolTableNode","cross_ref":"pydantic.types.SecretStr","kind":"Gdef","module_public":false},"ServerAuthenticationProvider":{".class":"SymbolTableNode","cross_ref":"chromadb.auth.ServerAuthenticationProvider","kind":"Gdef","module_public":false},"System":{".class":"SymbolTableNode","cross_ref":"chromadb.config.System","kind":"Gdef","module_public":false},"T":{".class":"SymbolTableNode","kind":"Gdef","module_public":false,"node":{".class":"TypeVarExpr","default":{".class":"AnyType","missing_import_name":null,"source_any":null,"type_of_any":4},"fullname":"chromadb.auth.token_authn.T","name":"T","upper_bound":"builtins.object","values":[],"variance":0}},"TokenAuthClientProvider":{".class":"SymbolTableNode","kind":"Gdef","node":{".class":"TypeInfo","_promote":[],"abstract_attributes":[],"alt_promote":null,"bases":["chromadb.auth.ClientAuthProvider"],"dataclass_transform_spec":null,"declared_metaclass":null,"defn":{".class":"ClassDef","fullname":"chromadb.auth.token_authn.TokenAuthClientProvider","name":"TokenAuthClientProvider","type_vars":[]},"deletable_attributes":[],"deprecated":null,"flags":[],"fullname":"chromadb.auth.token_authn.TokenAuthClientProvider","has_param_spec_type":false,"metaclass_type":"overrides.enforce.EnforceOverridesMeta","metadata":{},"module_name":"chromadb.auth.token_authn","mro":["chromadb.auth.token_authn.TokenAuthClientProvider","chromadb.auth.ClientAuthProvider","chromadb.config.Component","abc.ABC","overrides.enforce.EnforceOverrides","builtins.object"],"names":{".class":"SymbolTable","__init__":{".class":"SymbolTableNode","kind":"Mdef","node":{".class":"FuncDef","abstract_status":0,"arg_kinds":[0,0],"arg_names":["self","system"],"dataclass_transform_spec":null,"deprecated":null,"flags":[],"fullname":"chromadb.auth.token_authn.TokenAuthClientProvider.__init__","name":"__init__","type":{".class":"CallableType","arg_kinds":[0,0],"arg_names":["self","system"],"arg_types":["chromadb.auth.token_authn.TokenAuthClientProvider","chromadb.config.System"],"bound_args":[],"def_extras":{"first_arg":"self"},"fallback":"builtins.function","from_concatenate":false,"implicit":false,"imprecise_arg_kinds":false,"is_ellipsis_args":false,"name":"__init__ of TokenAuthClientProvider","ret_type":{".class":"NoneType"},"type_guard":null,"type_is":null,"unpack_kwargs":false,"variables":[]}}},"_settings":{".class":"SymbolTableNode","implicit":true,"kind":"Mdef","node":{".class":"Var","flags":["is_inferred"],"fullname":"chromadb.auth.token_authn.TokenAuthClientProvider._settings","name":"_settings","type":"chromadb.config.Settings"}},"_token":{".class":"SymbolTableNode","implicit":true,"kind":"Mdef","node":{".class":"Var","flags":["is_inferred"],"fullname":"chromadb.auth.token_authn.TokenAuthClientProvider._token","name":"_token","type":"pydantic.types.SecretStr"}},"_token_transport_header":{".class":"SymbolTableNode","implicit":true,"kind":"Mdef","node":{".class":"Var","flags":["is_inferred"],"fullname":"chromadb.auth.token_authn.TokenAuthClientProvider._token_transport_header","name":"_token_transport_header","type":"chromadb.auth.token_authn.TokenTransportHeader"}},"authenticate":{".class":"SymbolTableNode","kind":"Mdef","node":{".class":"Decorator","func":{".class":"FuncDef","abstract_status":0,"arg_kinds":[0],"arg_names":["self"],"dataclass_transform_spec":null,"deprecated":null,"flags":["is_decorated"],"fullname":"chromadb.auth.token_authn.TokenAuthClientProvider.authenticate","name":"authenticate","type":{".class":"CallableType","arg_kinds":[0],"arg_names":["self"],"arg_types":["chromadb.auth.token_authn.TokenAuthClientProvider"],"bound_args":[],"def_extras":{"first_arg":"self"},"fallback":"builtins.function","from_concatenate":false,"implicit":false,"imprecise_arg_kinds":false,"is_ellipsis_args":false,"name":"authenticate of TokenAuthClientProvider","ret_type":{".class":"TypeAliasType","args":[],"type_ref":"chromadb.auth.ClientAuthHeaders"},"type_guard":null,"type_is":null,"unpack_kwargs":false,"variables":[]}},"is_overload":false,"var":{".class":"Var","flags":["is_initialized_in_class","is_ready","is_inferred"],"fullname":"chromadb.auth.token_authn.TokenAuthClientProvider.authenticate","name":"authenticate","type":{".class":"CallableType","arg_kinds":[0],"arg_names":["self"],"arg_types":["chromadb.auth.token_authn.TokenAuthClientProvider"],"bound_args":[],"def_extras":{"first_arg":"self"},"fallback":"builtins.function","from_concatenate":false,"implicit":false,"imprecise_arg_kinds":false,"is_ellipsis_args":false,"name":"authenticate of TokenAuthClientProvider","ret_type":{".class":"TypeAliasType","args":[],"type_ref":"chromadb.auth.ClientAuthHeaders"},"type_guard":null,"type_is":null,"unpack_kwargs":false,"variables":[]}}}}},"self_type":{".class":"TypeVarType","default":{".class":"AnyType","missing_import_name":null,"source_any":null,"type_of_any":4},"fullname":"chromadb.auth.token_authn.TokenAuthClientProvider.Self","id":0,"name":"Self","namespace":"","upper_bound":"chromadb.auth.token_authn.TokenAuthClientProvider","values":[],"variance":0},"slots":null,"tuple_type":null,"type_vars":[],"typeddict_type":null}},"TokenAuthenticationServerProvider":{".class":"SymbolTableNode","kind":"Gdef","node":{".class":"TypeInfo","_promote":[],"abstract_attributes":[],"alt_promote":null,"bases":["chromadb.auth.ServerAuthenticationProvider"],"dataclass_transform_spec":null,"declared_metaclass":null,"defn":{".class":"ClassDef","fullname":"chromadb.auth.token_authn.TokenAuthenticationServerProvider","name":"TokenAuthenticationServerProvider","type_vars":[]},"deletable_attributes":[],"deprecated":null,"flags":[],"fullname":"chromadb.auth.token_authn.TokenAuthenticationServerProvider","has_param_spec_type":false,"metaclass_type":"overrides.enforce.EnforceOverridesMeta","metadata":{},"module_name":"chromadb.auth.token_authn","mro":["chromadb.auth.token_authn.TokenAuthenticationServerProvider","chromadb.auth.ServerAuthenticationProvider","chromadb.config.Component","abc.ABC","overrides.enforce.EnforceOverrides","builtins.object"],"names":{".class":"SymbolTable","__init__":{".class":"SymbolTableNode","kind":"Mdef","node":{".class":"FuncDef","abstract_status":0,"arg_kinds":[0,0],"arg_names":["self","system"],"dataclass_transform_spec":null,"deprecated":null,"flags":[],"fullname":"chromadb.auth.token_authn.TokenAuthenticationServerProvider.__init__","name":"__init__","type":{".class":"CallableType","arg_kinds":[0,0],"arg_names":["self","system"],"arg_types":["chromadb.auth.token_authn.TokenAuthenticationServerProvider","chromadb.config.System"],"bound_args":[],"def_extras":{"first_arg":"self"},"fallback":"builtins.function","from_concatenate":false,"implicit":false,"imprecise_arg_kinds":false,"is_ellipsis_args":false,"name":"__init__ of TokenAuthenticationServerProvider","ret_type":{".class":"NoneType"},"type_guard":null,"type_is":null,"unpack_kwargs":false,"variables":[]}}},"_settings":{".class":"SymbolTableNode","implicit":true,"kind":"Mdef","node":{".class":"Var","flags":["is_inferred"],"fullname":"chromadb.auth.token_authn.TokenAuthenticationServerProvider._settings","name":"_settings","type":"chromadb.config.Settings"}},"_token_transport_header":{".class":"SymbolTableNode","implicit":true,"kind":"Mdef","node":{".class":"Var","flags":["is_inferred"],"fullname":"chromadb.auth.token_authn.TokenAuthenticationServerProvider._token_transport_header","name":"_token_transport_header","type":"chromadb.auth.token_authn.TokenTransportHeader"}},"_token_user_mapping":{".class":"SymbolTableNode","implicit":true,"kind":"Mdef","node":{".class":"Var","flags":["explicit_self_type","is_ready","is_inferred"],"fullname":"chromadb.auth.token_authn.TokenAuthenticationServerProvider._token_user_mapping","name":"_token_user_mapping","type":{".class":"Instance","args":["builtins.str",{".class":"TypeAliasType","args":[],"type_ref":"chromadb.auth.token_authn.User"}],"extra_attrs":null,"type_ref":"builtins.dict"}}},"_users":{".class":"SymbolTableNode","implicit":true,"kind":"Mdef","node":{".class":"Var","flags":["is_inferred"],"fullname":"chromadb.auth.token_authn.TokenAuthenticationServerProvider._users","name":"_users","type":{".class":"Instance","args":[{".class":"TypeAliasType","args":[],"type_ref":"chromadb.auth.token_authn.User"}],"extra_attrs":null,"type_ref":"builtins.list"}}},"authenticate_or_raise":{".class":"SymbolTableNode","kind":"Mdef","node":{".class":"Decorator","func":{".class":"FuncDef","abstract_status":0,"arg_kinds":[0,0],"arg_names":["self","headers"],"dataclass_transform_spec":null,"deprecated":null,"flags":["is_decorated"],"fullname":"chromadb.auth.token_authn.TokenAuthenticationServerProvider.authenticate_or_raise","name":"authenticate_or_raise","type":{".class":"CallableType","arg_kinds":[0,0],"arg_names":["self","headers"],"arg_types":["chromadb.auth.token_authn.TokenAuthenticationServerProvider",{".class":"Instance","args":["builtins.str","builtins.str"],"extra_attrs":null,"type_ref":"builtins.dict"}],"bound_args":[],"def_extras":{"first_arg":"self"},"fallback":"builtins.function","from_concatenate":false,"implicit":false,"imprecise_arg_kinds":false,"is_ellipsis_args":false,"name":"authenticate_or_raise of TokenAuthenticationServerProvider","ret_type":"chromadb.auth.UserIdentity","type_guard":null,"type_is":null,"unpack_kwargs":false,"variables":[]}},"is_overload":false,"var":{".class":"Var","flags":["is_initialized_in_class","is_ready","is_inferred"],"fullname":"chromadb.auth.token_authn.TokenAuthenticationServerProvider.authenticate_or_raise","name":"authenticate_or_raise","type":{".class":"CallableType","arg_kinds":[0,0],"arg_names":["self","headers"],"arg_types":["chromadb.auth.token_authn.TokenAuthenticationServerProvider",{".class":"Instance","args":["builtins.str","builtins.str"],"extra_attrs":null,"type_ref":"builtins.dict"}],"bound_args":[],"def_extras":{"first_arg":"self"},"fallback":"builtins.function","from_concatenate":false,"implicit":false,"imprecise_arg_kinds":false,"is_ellipsis_args":false,"name":"authenticate_or_raise of TokenAuthenticationServerProvider","ret_type":"chromadb.auth.UserIdentity","type_guard":null,"type_is":null,"unpack_kwargs":false,"variables":[]}}}}},"self_type":{".class":"TypeVarType","default":{".class":"AnyType","missing_import_name":null,"source_any":null,"type_of_any":4},"fullname":"chromadb.auth.token_authn.TokenAuthenticationServerProvider.Self","id":0,"name":"Self","namespace":"","upper_bound":"chromadb.auth.token_authn.TokenAuthenticationServerProvider","values":[],"variance":0},"slots":null,"tuple_type":null,"type_vars":[],"typeddict_type":null}},"TokenTransportHeader":{".class":"SymbolTableNode","kind":"Gdef","node":{".class":"TypeInfo","_promote":[],"abstract_attributes":[],"alt_promote":null,"bases":["builtins.str","enum.Enum"],"dataclass_transform_spec":null,"declared_metaclass":null,"defn":{".class":"ClassDef","fullname":"chromadb.auth.token_authn.TokenTransportHeader","name":"TokenTransportHeader","type_vars":[]},"deletable_attributes":[],"deprecated":null,"flags":["is_enum"],"fullname":"chromadb.auth.token_authn.TokenTransportHeader","has_param_spec_type":false,"metaclass_type":"enum.EnumMeta","metadata":{},"module_name":"chromadb.auth.token_authn","mro":["chromadb.auth.token_authn.TokenTransportHeader","builtins.str","typing.Sequence","typing.Reversible","typing.Collection","typing.Iterable","typing.Container","enum.Enum","builtins.object"],"names":{".class":"SymbolTable","AUTHORIZATION":{".class":"SymbolTableNode","kind":"Mdef","node":{".class":"Var","flags":["is_initialized_in_class","is_final","is_ready","is_inferred","has_explicit_value"],"fullname":"chromadb.auth.token_authn.TokenTransportHeader.AUTHORIZATION","name":"AUTHORIZATION","type":{".class":"Instance","args":[],"extra_attrs":null,"last_known_value":{".class":"LiteralType","fallback":"builtins.str","value":"Authorization"},"type_ref":"builtins.str"}}},"X_CHROMA_TOKEN":{".class":"SymbolTableNode","kind":"Mdef","node":{".class":"Var","flags":["is_initialized_in_class","is_final","is_ready","is_inferred","has_explicit_value"],"fullname":"chromadb.auth.token_authn.TokenTransportHeader.X_CHROMA_TOKEN","name":"X_CHROMA_TOKEN","type":{".class":"Instance","args":[],"extra_attrs":null,"last_known_value":{".class":"LiteralType","fallback":"builtins.str","value":"X-Chroma-Token"},"type_ref":"builtins.str"}}}},"self_type":{".class":"TypeVarType","default":{".class":"AnyType","missing_import_name":null,"source_any":null,"type_of_any":4},"fullname":"chromadb.auth.token_authn.TokenTransportHeader.Self","id":0,"name":"Self","namespace":"","upper_bound":"chromadb.auth.token_authn.TokenTransportHeader","values":[],"variance":0},"slots":null,"tuple_type":null,"type_vars":[],"typeddict_type":null}},"TypeVar":{".class":"SymbolTableNode","cross_ref":"typing.TypeVar","kind":"Gdef","module_public":false},"TypedDict":{".class":"SymbolTableNode","cross_ref":"typing.TypedDict","kind":"Gdef","module_public":false},"User":{".class":"SymbolTableNode","kind":"Gdef","module_public":false,"node":{".class":"TypeInfo","_promote":[],"abstract_attributes":[],"alt_promote":null,"bases":["typing._TypedDict"],"dataclass_transform_spec":null,"declared_metaclass":null,"defn":{".class":"ClassDef","fullname":"chromadb.auth.token_authn.User","name":"User","type_vars":[]},"deletable_attributes":[],"deprecated":null,"flags":[],"fullname":"chromadb.auth.token_authn.User","has_param_spec_type":false,"metaclass_type":null,"metadata":{},"module_name":"chromadb.auth.token_authn","mro":["chromadb.auth.token_authn.User","typing._TypedDict","typing.Mapping","typing.Collection","typing.Iterable","typing.Container","builtins.object"],"names":{".class":"SymbolTable"},"self_type":null,"slots":null,"tuple_type":null,"type_vars":[],"typeddict_type":{".class":"TypedDictType","fallback":"typing._TypedDict","items":[["id","builtins.str"],["role","builtins.str"],["tenant",{".class":"UnionType","items":["builtins.str",{".class":"NoneType"}],"uses_pep604_syntax":false}],["databases",{".class":"UnionType","items":[{".class":"Instance","args":["builtins.str"],"extra_attrs":null,"type_ref":"builtins.list"},{".class":"NoneType"}],"uses_pep604_syntax":false}],["tokens",{".class":"Instance","args":["builtins.str"],"extra_attrs":null,"type_ref":"builtins.list"}]],"readonly_keys":[],"required_keys":["databases","id","role","tenant","tokens"]}}},"UserIdentity":{".class":"SymbolTableNode","cross_ref":"chromadb.auth.UserIdentity","kind":"Gdef","module_public":false},"__all__":{".class":"SymbolTableNode","kind":"Gdef","module_public":false,"node":{".class":"Var","flags":["is_inferred","has_explicit_value"],"fullname":"chromadb.auth.token_authn.__all__","name":"__all__","type":{".class":"Instance","args":["builtins.str"],"extra_attrs":null,"type_ref":"builtins.list"}}},"__annotations__":{".class":"SymbolTableNode","kind":"Gdef","module_public":false,"node":{".class":"Var","flags":["is_ready"],"fullname":"chromadb.auth.token_authn.__annotations__","name":"__annotations__","type":{".class":"Instance","args":["builtins.str",{".class":"AnyType","missing_import_name":null,"source_any":null,"type_of_any":6}],"extra_attrs":null,"type_ref":"builtins.dict"}}},"__doc__":{".class":"SymbolTableNode","kind":"Gdef","module_public":false,"node":{".class":"Var","flags":["is_ready"],"fullname":"chromadb.auth.token_authn.__doc__","name":"__doc__","type":"builtins.str"}},"__file__":{".class":"SymbolTableNode","kind":"Gdef","module_public":false,"node":{".class":"Var","flags":["is_ready"],"fullname":"chromadb.auth.token_authn.__file__","name":"__file__","type":"builtins.str"}},"__name__":{".class":"SymbolTableNode","kind":"Gdef","module_public":false,"node":{".class":"Var","flags":["is_ready"],"fullname":"chromadb.auth.token_authn.__name__","name":"__name__","type":"builtins.str"}},"__package__":{".class":"SymbolTableNode","kind":"Gdef","module_public":false,"node":{".class":"Var","flags":["is_ready"],"fullname":"chromadb.auth.token_authn.__package__","name":"__package__","type":"builtins.str"}},"__path__":{".class":"SymbolTableNode","kind":"Gdef","module_public":false,"node":{".class":"Var","flags":["is_ready"],"fullname":"chromadb.auth.token_authn.__path__","name":"__path__","type":{".class":"Instance","args":["builtins.str"],"extra_attrs":null,"type_ref":"builtins.list"}}},"__spec__":{".class":"SymbolTableNode","kind":"Gdef","module_public":false,"node":{".class":"Var","flags":["is_ready"],"fullname":"chromadb.auth.token_authn.__spec__","name":"__spec__","type":"_frozen_importlib.ModuleSpec"}},"_check_allowed_token_headers":{".class":"SymbolTableNode","kind":"Gdef","module_public":false,"node":{".class":"FuncDef","abstract_status":0,"arg_kinds":[0],"arg_names":["token_header"],"dataclass_transform_spec":null,"deprecated":null,"flags":[],"fullname":"chromadb.auth.token_authn._check_allowed_token_headers","name":"_check_allowed_token_headers","type":{".class":"CallableType","arg_kinds":[0],"arg_names":["token_header"],"arg_types":["builtins.str"],"bound_args":[],"def_extras":{"first_arg":null},"fallback":"builtins.function","from_concatenate":false,"implicit":false,"imprecise_arg_kinds":false,"is_ellipsis_args":false,"name":"_check_allowed_token_headers","ret_type":{".class":"NoneType"},"type_guard":null,"type_is":null,"unpack_kwargs":false,"variables":[]}}},"_check_token":{".class":"SymbolTableNode","kind":"Gdef","module_public":false,"node":{".class":"FuncDef","abstract_status":0,"arg_kinds":[0],"arg_names":["token"],"dataclass_transform_spec":null,"deprecated":null,"flags":[],"fullname":"chromadb.auth.token_authn._check_token","name":"_check_token","type":{".class":"CallableType","arg_kinds":[0],"arg_names":["token"],"arg_types":["builtins.str"],"bound_args":[],"def_extras":{"first_arg":null},"fallback":"builtins.function","from_concatenate":false,"implicit":false,"imprecise_arg_kinds":false,"is_ellipsis_args":false,"name":"_check_token","ret_type":{".class":"NoneType"},"type_guard":null,"type_is":null,"unpack_kwargs":false,"variables":[]}}},"allowed_token_headers":{".class":"SymbolTableNode","kind":"Gdef","module_public":false,"node":{".class":"Var","flags":["is_inferred","has_explicit_value"],"fullname":"chromadb.auth.token_authn.allowed_token_headers","name":"allowed_token_headers","type":{".class":"Instance","args":["builtins.str"],"extra_attrs":null,"type_ref":"builtins.list"}}},"cast":{".class":"SymbolTableNode","cross_ref":"typing.cast","kind":"Gdef","module_public":false},"logger":{".class":"SymbolTableNode","kind":"Gdef","module_public":false,"node":{".class":"Var","flags":["is_inferred","has_explicit_value"],"fullname":"chromadb.auth.token_authn.logger","name":"logger","type":"logging.Logger"}},"logging":{".class":"SymbolTableNode","cross_ref":"logging","kind":"Gdef","module_public":false},"override":{".class":"SymbolTableNode","cross_ref":"overrides.overrides.override","kind":"Gdef","module_public":false},"random":{".class":"SymbolTableNode","cross_ref":"random","kind":"Gdef","module_public":false},"re":{".class":"SymbolTableNode","cross_ref":"re","kind":"Gdef","module_public":false},"string":{".class":"SymbolTableNode","cross_ref":"string","kind":"Gdef","module_public":false},"time":{".class":"SymbolTableNode","cross_ref":"time","kind":"Gdef","module_public":false},"trace_method":{".class":"SymbolTableNode","cross_ref":"chromadb.telemetry.opentelemetry.trace_method","kind":"Gdef","module_public":false},"traceback":{".class":"SymbolTableNode","cross_ref":"traceback","kind":"Gdef","module_public":false},"valid_token_chars":{".class":"SymbolTableNode","kind":"Gdef","module_public":false,"node":{".class":"Var","flags":["is_inferred","has_explicit_value"],"fullname":"chromadb.auth.token_authn.valid_token_chars","name":"valid_token_chars","type":{".class":"Instance","args":["builtins.str"],"extra_attrs":null,"type_ref":"builtins.set"}}},"yaml":{".class":"SymbolTableNode","kind":"Gdef","module_public":false,"node":{".class":"Var","flags":["is_suppressed_import","is_ready","is_inferred"],"fullname":"chromadb.auth.token_authn.yaml","name":"yaml","type":{".class":"AnyType","missing_import_name":"chromadb.auth.token_authn.yaml","source_any":null,"type_of_any":3}}}},"path":"c:\\Users\\chaic\\AppData\\Local\\Programs\\Python\\Python313\\Lib\\site-packages\\chromadb\\auth\\token_authn\\__init__.py"}