{".class":"MypyFile","_fullname":"redis.commands.vectorset","future_import_flags":[],"is_partial_stub_package":false,"is_stub":false,"names":{".class":"SymbolTable","VEMB_CMD":{".class":"SymbolTableNode","cross_ref":"redis.commands.vectorset.commands.VEMB_CMD","kind":"Gdef"},"VGETATTR_CMD":{".class":"SymbolTableNode","cross_ref":"redis.commands.vectorset.commands.VGETATTR_CMD","kind":"Gdef"},"VINFO_CMD":{".class":"SymbolTableNode","cross_ref":"redis.commands.vectorset.commands.VINFO_CMD","kind":"Gdef"},"VLINKS_CMD":{".class":"SymbolTableNode","cross_ref":"redis.commands.vectorset.commands.VLINKS_CMD","kind":"Gdef"},"VSIM_CMD":{".class":"SymbolTableNode","cross_ref":"redis.commands.vectorset.commands.VSIM_CMD","kind":"Gdef"},"VectorSet":{".class":"SymbolTableNode","kind":"Gdef","node":{".class":"TypeInfo","_promote":[],"abstract_attributes":[["execute_command",2]],"alt_promote":null,"bases":["redis.commands.vectorset.commands.VectorSetCommands"],"dataclass_transform_spec":null,"declared_metaclass":null,"defn":{".class":"ClassDef","fullname":"redis.commands.vectorset.VectorSet","name":"VectorSet","type_vars":[]},"deletable_attributes":[],"deprecated":null,"flags":["is_abstract"],"fullname":"redis.commands.vectorset.VectorSet","has_param_spec_type":false,"metaclass_type":"abc.ABCMeta","metadata":{},"module_name":"redis.commands.vectorset","mro":["redis.commands.vectorset.VectorSet","redis.commands.vectorset.commands.VectorSetCommands","redis.typing.CommandsProtocol","builtins.object"],"names":{".class":"SymbolTable","_MODULE_CALLBACKS":{".class":"SymbolTableNode","implicit":true,"kind":"Mdef","node":{".class":"Var","flags":["is_inferred"],"fullname":"redis.commands.vectorset.VectorSet._MODULE_CALLBACKS","name":"_MODULE_CALLBACKS","type":{".class":"AnyType","missing_import_name":null,"source_any":null,"type_of_any":1}}},"_RESP2_MODULE_CALLBACKS":{".class":"SymbolTableNode","implicit":true,"kind":"Mdef","node":{".class":"Var","flags":["is_inferred"],"fullname":"redis.commands.vectorset.VectorSet._RESP2_MODULE_CALLBACKS","name":"_RESP2_MODULE_CALLBACKS","type":{".class":"AnyType","missing_import_name":null,"source_any":null,"type_of_any":1}}},"_RESP3_MODULE_CALLBACKS":{".class":"SymbolTableNode","implicit":true,"kind":"Mdef","node":{".class":"Var","flags":["is_inferred"],"fullname":"redis.commands.vectorset.VectorSet._RESP3_MODULE_CALLBACKS","name":"_RESP3_MODULE_CALLBACKS","type":{".class":"AnyType","missing_import_name":null,"source_any":null,"type_of_any":1}}},"__init__":{".class":"SymbolTableNode","kind":"Mdef","node":{".class":"FuncDef","abstract_status":0,"arg_kinds":[0,0,4],"arg_names":["self","client","kwargs"],"dataclass_transform_spec":null,"deprecated":null,"flags":[],"fullname":"redis.commands.vectorset.VectorSet.__init__","name":"__init__","type":null}},"client":{".class":"SymbolTableNode","implicit":true,"kind":"Mdef","node":{".class":"Var","flags":["is_inferred"],"fullname":"redis.commands.vectorset.VectorSet.client","name":"client","type":{".class":"AnyType","missing_import_name":null,"source_any":null,"type_of_any":1}}}},"self_type":{".class":"TypeVarType","default":{".class":"AnyType","missing_import_name":null,"source_any":null,"type_of_any":4},"fullname":"redis.commands.vectorset.VectorSet.Self","id":0,"name":"Self","namespace":"","upper_bound":"redis.commands.vectorset.VectorSet","values":[],"variance":0},"slots":null,"tuple_type":null,"type_vars":[],"typeddict_type":null}},"VectorSetCommands":{".class":"SymbolTableNode","cross_ref":"redis.commands.vectorset.commands.VectorSetCommands","kind":"Gdef"},"__annotations__":{".class":"SymbolTableNode","kind":"Gdef","node":{".class":"Var","flags":["is_ready"],"fullname":"redis.commands.vectorset.__annotations__","name":"__annotations__","type":{".class":"Instance","args":["builtins.str",{".class":"AnyType","missing_import_name":null,"source_any":null,"type_of_any":6}],"extra_attrs":null,"type_ref":"builtins.dict"}}},"__doc__":{".class":"SymbolTableNode","kind":"Gdef","node":{".class":"Var","flags":["is_ready"],"fullname":"redis.commands.vectorset.__doc__","name":"__doc__","type":"builtins.str"}},"__file__":{".class":"SymbolTableNode","kind":"Gdef","node":{".class":"Var","flags":["is_ready"],"fullname":"redis.commands.vectorset.__file__","name":"__file__","type":"builtins.str"}},"__name__":{".class":"SymbolTableNode","kind":"Gdef","node":{".class":"Var","flags":["is_ready"],"fullname":"redis.commands.vectorset.__name__","name":"__name__","type":"builtins.str"}},"__package__":{".class":"SymbolTableNode","kind":"Gdef","node":{".class":"Var","flags":["is_ready"],"fullname":"redis.commands.vectorset.__package__","name":"__package__","type":"builtins.str"}},"__path__":{".class":"SymbolTableNode","kind":"Gdef","node":{".class":"Var","flags":["is_ready"],"fullname":"redis.commands.vectorset.__path__","name":"__path__","type":{".class":"Instance","args":["builtins.str"],"extra_attrs":null,"type_ref":"builtins.list"}}},"__spec__":{".class":"SymbolTableNode","kind":"Gdef","node":{".class":"Var","flags":["is_ready"],"fullname":"redis.commands.vectorset.__spec__","name":"__spec__","type":"_frozen_importlib.ModuleSpec"}},"get_protocol_version":{".class":"SymbolTableNode","cross_ref":"redis.commands.helpers.get_protocol_version","kind":"Gdef"},"json":{".class":"SymbolTableNode","cross_ref":"json","kind":"Gdef"},"pairs_to_dict":{".class":"SymbolTableNode","cross_ref":"redis._parsers.helpers.pairs_to_dict","kind":"Gdef"},"parse_vemb_result":{".class":"SymbolTableNode","cross_ref":"redis.commands.vectorset.utils.parse_vemb_result","kind":"Gdef"},"parse_vlinks_result":{".class":"SymbolTableNode","cross_ref":"redis.commands.vectorset.utils.parse_vlinks_result","kind":"Gdef"},"parse_vsim_result":{".class":"SymbolTableNode","cross_ref":"redis.commands.vectorset.utils.parse_vsim_result","kind":"Gdef"}},"path":"c:\\Users\\chaic\\AppData\\Local\\Programs\\Python\\Python313\\Lib\\site-packages\\redis\\commands\\vectorset\\__init__.py"}