{"data_mtime":1749047255,"dep_lines":[20,23,4,9,20,21,22,1075,1317,2,3,4,5,6,7,8,10,11,12,13,14,15,16,17,18,20,1,1,1,1,1,1,1,1,1,1,1,1,1,1,1,1,1,1,1,1,1,1,1,1,1,1,1,1,1,1,1,1,1,1],"dep_prios":[10,5,10,10,20,5,5,20,10,10,10,20,10,10,10,10,10,10,10,10,10,5,5,5,5,20,5,20,20,20,20,20,30,30,30,30,30,30,30,30,30,30,30,30,30,20,20,20,20,20,20,20,20,20,20,20,20,20,20,20],"dependencies":["torch._logging.structured","torch.utils._traceback","importlib.util","os.path","torch._logging","torch._guards","torch._utils_internal","torch.version","torch.distributed","functools","hashlib","importlib","itertools","json","logging","os","pathlib","re","sys","tempfile","time","collections","dataclasses","typing","weakref","torch","builtins","multiprocessing.reduction","math","operator","torch.nn","torch.distributed._functional_collectives","_collections_abc","_frozen_importlib","_io","_typeshed","_weakrefset","abc","enum","genericpath","io","json.encoder","torch._C","torch._C._distributed_c10d","torch.distributed.distributed_c10d","types","string","html","copy","contextlib","inspect","pprint","warnings","traceback","altair.vegalite.v5.schema.channels","altair.vegalite.v5.schema","altair.vegalite.v5.schema.mixins","altair.vegalite.v5.api","altair.vegalite.v5.schema.core","altair.vegalite.v5.compiler"],"hash":"9aaf69607764f93a107a466f84ef079bdbfe06a2","id":"torch._logging._internal","ignore_all":true,"interface_hash":"0ea759c6b8e2308d9d1d471b4879dba2c9feb801","mtime":1748765140,"options":{"allow_redefinition":false,"allow_untyped_globals":false,"always_false":[],"always_true":[],"bazel":false,"check_untyped_defs":false,"disable_bytearray_promotion":false,"disable_error_code":[],"disable_memoryview_promotion":false,"disabled_error_codes":[],"disallow_any_decorated":false,"disallow_any_explicit":false,"disallow_any_expr":false,"disallow_any_generics":false,"disallow_any_unimported":false,"disallow_incomplete_defs":false,"disallow_subclassing_any":false,"disallow_untyped_calls":false,"disallow_untyped_decorators":false,"disallow_untyped_defs":false,"enable_error_code":[],"enabled_error_codes":[],"extra_checks":false,"follow_imports":"normal","follow_imports_for_stubs":false,"follow_untyped_imports":false,"ignore_errors":false,"ignore_missing_imports":false,"implicit_optional":false,"implicit_reexport":true,"local_partial_types":false,"mypyc":false,"old_type_inference":false,"platform":"win32","plugins":[],"strict_bytes":false,"strict_concatenate":false,"strict_equality":false,"strict_optional":true,"warn_no_return":true,"warn_return_any":false,"warn_unreachable":false,"warn_unused_ignores":false},"path":"c:\\Users\\chaic\\AppData\\Local\\Programs\\Python\\Python313\\Lib\\site-packages\\torch\\_logging\\_internal.py","plugin_data":null,"size":48666,"suppressed":[],"version_id":"1.15.0"}